wessql/__init__.py
wessql/wessql.py
wessql-0.0.2.dist-info/LICENSE.txt
wessql-0.0.2.dist-info/METADATA
wessql-0.0.2.dist-info/WHEEL
wessql-0.0.2.dist-info/top_level.txt
wessql-0.0.2.dist-info/RECORD
