Metadata-Version: 2.1
Name: wessql
Version: 0.0.2
Summary: This is the simplest module for quick work with sqlite3.
Home-page: https://github.com/JohnyWessel/simple-database
Author: w3ssel
Author-email: johnywessel@gmail.com
Project-URL: GitHub, https://github.com/johnywessel
Keywords: wessql
Classifier: Programming Language :: Python :: 3.11
Classifier: License :: OSI Approved :: MIT License
Classifier: Operating System :: OS Independent
Requires-Python: >=3.1.1
License-File: LICENSE.txt
Requires-Dist: requests >=2.25.1
